LICENSE
MANIFEST.in
README.rst
example.conf
polycomp
polycomp.py
setup.cfg
setup.py
polycomp.egg-info/PKG-INFO
polycomp.egg-info/SOURCES.txt
polycomp.egg-info/dependency_links.txt
polycomp.egg-info/pbr.json
polycomp.egg-info/requires.txt
polycomp.egg-info/top_level.txt
pypolycomp/__init__.py
pypolycomp/_bindings.c
pypolycomp/_bindings.pyx
pypolycomp/cpolycomp.pxd
pypolycomp/optimization.py
pypolycomp/version.py