Metadata-Version: 1.1
Name: polycomp
Version: 1.0.4
Summary: Python bindings to the libpolycomp C library
Home-page: https://github.com/ziotom78/polycomp
Author: Maurizio Tomasi
Author-email: ziotom78@gmail.com
License: MIT
Keywords: compression astronomy fits
Platform: UNKNOWN
Classifier: Development Status :: 4 - Beta
Classifier: Intended Audience :: Science/Research
Classifier: Topic :: System :: Archiving :: Compression
Classifier: License :: OSI Approved :: MIT License
Classifier: Operating System :: POSIX
Classifier: Programming Language :: Python :: 2
Classifier: Programming Language :: Python :: 2.7
Classifier: Programming Language :: Python :: 3
Classifier: Programming Language :: Python :: 3.4
